jamostoolkit/__init__.py
jamostoolkit/jamostoolkit.py
jamos_toolkit-1.7.dist-info/LICENSE
jamos_toolkit-1.7.dist-info/METADATA
jamos_toolkit-1.7.dist-info/WHEEL
jamos_toolkit-1.7.dist-info/top_level.txt
jamos_toolkit-1.7.dist-info/RECORD
